AndroidStudioZhongwenJiaochengQianLiuzhang/README.md
AndroidStudioZhongwenJiaochengQianLiuzhang/__init__.py
AndroidStudioZhongwenJiaochengQianLiuzhang/__main__.py
AndroidStudioZhongwenJiaochengQianLiuzhang/file.epub
AndroidStudioZhongwenJiaochengQianLiuzhang/index.html
AndroidStudioZhongwenJiaochengQianLiuzhang/css/__init__.py
AndroidStudioZhongwenJiaochengQianLiuzhang/css/annotations.css
AndroidStudioZhongwenJiaochengQianLiuzhang/css/main.css
AndroidStudioZhongwenJiaochengQianLiuzhang/css/normalize.css
AndroidStudioZhongwenJiaochengQianLiuzhang/css/popup.css
AndroidStudioZhongwenJiaochengQianLiuzhang/font/__init__.py
AndroidStudioZhongwenJiaochengQianLiuzhang/font/fontello.eot
AndroidStudioZhongwenJiaochengQianLiuzhang/font/fontello.svg
AndroidStudioZhongwenJiaochengQianLiuzhang/font/fontello.ttf
AndroidStudioZhongwenJiaochengQianLiuzhang/font/fontello.woff
AndroidStudioZhongwenJiaochengQianLiuzhang/img/__init__.py
AndroidStudioZhongwenJiaochengQianLiuzhang/img/annotator-glyph-sprite.png
AndroidStudioZhongwenJiaochengQianLiuzhang/img/annotator-icon-sprite.png
AndroidStudioZhongwenJiaochengQianLiuzhang/img/apple-touch-icon.png
AndroidStudioZhongwenJiaochengQianLiuzhang/img/cancelfullscreen.png
AndroidStudioZhongwenJiaochengQianLiuzhang/img/close.png
AndroidStudioZhongwenJiaochengQianLiuzhang/img/fullscreen.png
AndroidStudioZhongwenJiaochengQianLiuzhang/img/loader.gif
AndroidStudioZhongwenJiaochengQianLiuzhang/img/menu-icon.png
AndroidStudioZhongwenJiaochengQianLiuzhang/img/save.png
AndroidStudioZhongwenJiaochengQianLiuzhang/img/saved.png
AndroidStudioZhongwenJiaochengQianLiuzhang/img/settings-s.png
AndroidStudioZhongwenJiaochengQianLiuzhang/img/settings.png
AndroidStudioZhongwenJiaochengQianLiuzhang/img/star.png
AndroidStudioZhongwenJiaochengQianLiuzhang/js/__init__.py
AndroidStudioZhongwenJiaochengQianLiuzhang/js/epub.js
AndroidStudioZhongwenJiaochengQianLiuzhang/js/epub.min.js
AndroidStudioZhongwenJiaochengQianLiuzhang/js/epub.min.map
android_studio_zhongwen_jiaocheng_qian_liuzhang-2024.2.29.0.dist-info/METADATA
android_studio_zhongwen_jiaocheng_qian_liuzhang-2024.2.29.0.dist-info/WHEEL
android_studio_zhongwen_jiaocheng_qian_liuzhang-2024.2.29.0.dist-info/entry_points.txt
android_studio_zhongwen_jiaocheng_qian_liuzhang-2024.2.29.0.dist-info/top_level.txt
android_studio_zhongwen_jiaocheng_qian_liuzhang-2024.2.29.0.dist-info/RECORD
